optimum/commands/export/onnx.py
optimum/commands/onnxruntime/base.py
optimum/commands/onnxruntime/optimize.py
optimum/commands/onnxruntime/quantize.py
optimum/commands/register/register_export.py
optimum/commands/register/register_onnxruntime.py
optimum/exporters/onnx/__init__.py
optimum/exporters/onnx/__main__.py
optimum/exporters/onnx/_traceable_cache.py
optimum/exporters/onnx/_traceable_decorator.py
optimum/exporters/onnx/base.py
optimum/exporters/onnx/config.py
optimum/exporters/onnx/constants.py
optimum/exporters/onnx/convert.py
optimum/exporters/onnx/input_generators.py
optimum/exporters/onnx/model_configs.py
optimum/exporters/onnx/model_patcher.py
optimum/exporters/onnx/utils.py
optimum/onnx/__init__.py
optimum/onnx/graph_transformations.py
optimum/onnx/transformations_utils.py
optimum/onnx/utils.py
optimum/onnx/version.py
optimum/onnxruntime/__init__.py
optimum/onnxruntime/base.py
optimum/onnxruntime/configuration.py
optimum/onnxruntime/constants.py
optimum/onnxruntime/dummy_objects.py
optimum/onnxruntime/modeling.py
optimum/onnxruntime/modeling_decoder.py
optimum/onnxruntime/modeling_diffusion.py
optimum/onnxruntime/modeling_ort.py
optimum/onnxruntime/modeling_seq2seq.py
optimum/onnxruntime/optimization.py
optimum/onnxruntime/pipelines.py
optimum/onnxruntime/quantization.py
optimum/onnxruntime/utils.py
optimum/onnxruntime/preprocessors/__init__.py
optimum/onnxruntime/preprocessors/quantization.py
optimum/onnxruntime/preprocessors/passes/__init__.py
optimum/onnxruntime/preprocessors/passes/excluders.py
optimum/onnxruntime/preprocessors/passes/fully_connected.py
optimum/onnxruntime/preprocessors/passes/gelu.py
optimum/onnxruntime/preprocessors/passes/layernorm.py
optimum_onnx-0.0.2.dist-info/licenses/LICENSE
optimum_onnx-0.0.2.dist-info/METADATA
optimum_onnx-0.0.2.dist-info/WHEEL
optimum_onnx-0.0.2.dist-info/top_level.txt
optimum_onnx-0.0.2.dist-info/RECORD
