Metadata-Version: 2.4
Name: optimum-onnx
Version: 0.0.2
Summary: Optimum ONNX is an interface between the Hugging Face libraries and ONNX / ONNX Runtime
Author-email: "HuggingFace Inc. Special Ops Team" <hardware@huggingface.co>
License: Apache-2.0
Project-URL: Homepage, https://github.com/huggingface/optimum-onnx
Keywords: transformers,quantization,inference,onnx,onnxruntime
Classifier: Development Status :: 2 - Pre-Alpha
Classifier: License :: OSI Approved :: Apache Software License
Classifier: Intended Audience :: Developers
Classifier: Intended Audience :: Education
Classifier: Intended Audience :: Science/Research
Classifier: Operating System :: OS Independent
Classifier: Programming Language :: Python :: 3
Classifier: Programming Language :: Python :: 3.9
Classifier: Programming Language :: Python :: 3.10
Classifier: Programming Language :: Python :: 3.11
Classifier: Programming Language :: Python :: 3.12
Classifier: Programming Language :: Python :: 3.13
Classifier: Topic :: Scientific/Engineering :: Artificial Intelligence
Requires-Python: >=3.9.0
License-File: LICENSE
Requires-Dist: optimum~=2.0.0
Requires-Dist: transformers<4.56.0,>=4.36.0
Requires-Dist: onnx
Provides-Extra: onnxruntime
Requires-Dist: onnxruntime>=1.18.0; extra == "onnxruntime"
Provides-Extra: onnxruntime-gpu
Requires-Dist: onnxruntime-gpu>=1.18.0; extra == "onnxruntime-gpu"
Provides-Extra: tests
Requires-Dist: accelerate>=0.26.0; extra == "tests"
Requires-Dist: datasets; extra == "tests"
Requires-Dist: einops; extra == "tests"
Requires-Dist: hf_xet; extra == "tests"
Requires-Dist: parameterized; extra == "tests"
Requires-Dist: Pillow; extra == "tests"
Requires-Dist: pytest-xdist; extra == "tests"
Requires-Dist: pytest; extra == "tests"
Requires-Dist: safetensors; extra == "tests"
Requires-Dist: scipy; extra == "tests"
Requires-Dist: sentencepiece; extra == "tests"
Requires-Dist: timm; extra == "tests"
Requires-Dist: onnxslim>=0.1.60; extra == "tests"
Requires-Dist: rjieba; extra == "tests"
Requires-Dist: sacremoses; extra == "tests"
Provides-Extra: quality
Requires-Dist: ruff==0.12.3; extra == "quality"
Dynamic: license-file
